esoterrible/__init__.py
esoterrible/butterfinger_booleans.py
esoterrible/code_language_detection.py
esoterrible/esrever.py
esoterrible/looks_optimised_to_me.py
esoterrible/oxford_dictionary.py
esoterrible/resources/__init__.py
esoterrible/resources/uk_words.txt
esoterrible/resources/us_words.txt
esoterrible-0.1.2.dist-info/LICENSE.txt
esoterrible-0.1.2.dist-info/METADATA
esoterrible-0.1.2.dist-info/WHEEL
esoterrible-0.1.2.dist-info/top_level.txt
esoterrible-0.1.2.dist-info/RECORD
