Metadata-Version: 2.1
Name: esoterrible
Version: 0.1.2
Summary: Some terrible features you can add to Python
Home-page: https://github.com/rach-sharp/esoterrible
Author: Rach Sharp
Author-email: me@rachsharp.co.uk
License: MIT
Platform: UNKNOWN
Classifier: License :: OSI Approved :: MIT License
Classifier: Programming Language :: Python
Classifier: Programming Language :: Python :: 3
Requires-Python: >=3.6.0
Requires-Dist: distance
Requires-Dist: pytz
Requires-Dist: PyDictionary
